pywrkstinfo.py
pywrkstinfo-0.1.8.dist-info/LICENSE
pywrkstinfo-0.1.8.dist-info/METADATA
pywrkstinfo-0.1.8.dist-info/WHEEL
pywrkstinfo-0.1.8.dist-info/entry_points.txt
pywrkstinfo-0.1.8.dist-info/top_level.txt
pywrkstinfo-0.1.8.dist-info/RECORD
