Metadata-Version: 2.2
Name: pywrkstinfo
Version: 0.1.8
Summary: Conceptual workstation information output.
Author-email: bitdruid <bitdruid@outlook.com>
License: MIT License
Project-URL: Homepage, https://github.com/bitdruid/forensic_concepts
Keywords: bash,shell,tracking,logging
Classifier: Programming Language :: Python :: 3.6
Classifier: License :: OSI Approved :: MIT License
Classifier: Operating System :: OS Independent
Requires-Python: >=3.6
License-File: LICENSE
Requires-Dist: psutil==6.1.1
Requires-Dist: distro==1.9.0
Requires-Dist: tabulate==0.9.0
